wanglib-0.1.6.dist-info/METADATA
wanglib-0.1.6.dist-info/WHEEL
wanglib-0.1.6.dist-info/entry_points.txt
wanglib-0.1.6.dist-info/licenses/LICENSE
wanglib/__init__.py
wanglib/cache/__init__.py
wanglib/file/__init__.py
wanglib/log/__init__.py
wanglib/message/__init__.py
wanglib-0.1.6.dist-info/RECORD
