Metadata-Version: 2.1
Name: wanglib
Version: 0.1.6
Summary: 机器狗的Python前置包！
Author-Email: machinacanis <hf4minecraft@163.com>
License: MIT
Project-URL: Homepage, https://github.com/machinacanis/wanglib
Project-URL: Issues, https://github.com/machinacanis/wanglib/issues
Requires-Python: >=3.12
Requires-Dist: loguru>=0.7.3
Requires-Dist: cachetools>=5.5.2
Requires-Dist: httpx>=0.28.1
